deepqmc/__init__.py
deepqmc/__main__.py
deepqmc/app.py
deepqmc/ewm.py
deepqmc/exceptions.py
deepqmc/fit.py
deepqmc/force.py
deepqmc/hamil.py
deepqmc/hkext.py
deepqmc/kfacext.py
deepqmc/log.py
deepqmc/molecule.py
deepqmc/observable.py
deepqmc/optimizer.py
deepqmc/oscillator_strength.py
deepqmc/parallel.py
deepqmc/physics.py
deepqmc/train.py
deepqmc/types.py
deepqmc/units.py
deepqmc/utils.py
deepqmc/validate_kwargs.py
deepqmc/conf/__init__.py
deepqmc/conf/config.yaml
deepqmc/conf/config_slurm.yaml
deepqmc/conf/custom_resolvers.py
deepqmc/conf/ansatz/deeperwin.yaml
deepqmc/conf/ansatz/default.yaml
deepqmc/conf/ansatz/ferminet.yaml
deepqmc/conf/ansatz/psiformer.yaml
deepqmc/conf/hamil/qc.yaml
deepqmc/conf/hamil/qc_forward_laplacian.yaml
deepqmc/conf/hamil/mol/B.yaml
deepqmc/conf/hamil/mol/B2.yaml
deepqmc/conf/hamil/mol/Be.yaml
deepqmc/conf/hamil/mol/Be2.yaml
deepqmc/conf/hamil/mol/C.yaml
deepqmc/conf/hamil/mol/C2.yaml
deepqmc/conf/hamil/mol/CH2O.yaml
deepqmc/conf/hamil/mol/CH4.yaml
deepqmc/conf/hamil/mol/CO.yaml
deepqmc/conf/hamil/mol/CO2.yaml
deepqmc/conf/hamil/mol/H.yaml
deepqmc/conf/hamil/mol/H10.yaml
deepqmc/conf/hamil/mol/H2+.yaml
deepqmc/conf/hamil/mol/H2.yaml
deepqmc/conf/hamil/mol/H2O.yaml
deepqmc/conf/hamil/mol/H2O3.yaml
deepqmc/conf/hamil/mol/He.yaml
deepqmc/conf/hamil/mol/Li2.yaml
deepqmc/conf/hamil/mol/LiH.yaml
deepqmc/conf/hamil/mol/LiNH3_6.yaml
deepqmc/conf/hamil/mol/N2.yaml
deepqmc/conf/hamil/mol/NH3.yaml
deepqmc/conf/hamil/mol/Sc.yaml
deepqmc/conf/hamil/mol/ScO.yaml
deepqmc/conf/hamil/mol/bicyclobutane.yaml
deepqmc/conf/hamil/mol/cyclobutadiene_square.yaml
deepqmc/conf/hamil/mol/from_file.yaml
deepqmc/conf/hydra/help/custom.yaml
deepqmc/conf/hydra/job_logging/custom.yaml
deepqmc/conf/hydra/launcher/slurm.yaml
deepqmc/conf/task/evaluate.yaml
deepqmc/conf/task/evaluate_forces.yaml
deepqmc/conf/task/restart.yaml
deepqmc/conf/task/train.yaml
deepqmc/conf/task/train_excited_psiformer.yaml
deepqmc/conf/task/train_ferminet.yaml
deepqmc-1.2.0.dist-info/LICENSE
deepqmc-1.2.0.dist-info/METADATA
deepqmc-1.2.0.dist-info/WHEEL
deepqmc-1.2.0.dist-info/entry_points.txt
deepqmc-1.2.0.dist-info/top_level.txt
deepqmc-1.2.0.dist-info/RECORD
