Metadata-Version: 2.1
Name: deepqmc
Version: 1.2.0
Summary: Deep-learning quantum Monte Carlo for electrons in real space
Author: Jan Hermann
Author-email: Zeno Schätzle <zeno.schaetzle@fu-berlin.de>, Péter Bernát Szabó <peter.bernat.szabo@fu-berlin.de>
Maintainer-email: Zeno Schätzle <zeno.schaetzle@fu-berlin.de>, Péter Bernát Szabó <peter.bernat.szabo@fu-berlin.de>
License: MIT
Project-URL: repository, https://github.com/deepqmc/deepqmc
Project-URL: documentation, https://deepqmc.github.io
Classifier: Development Status :: 4 - Beta
Classifier: Environment :: Console
Classifier: Environment :: GPU :: NVIDIA CUDA
Classifier: Intended Audience :: Science/Research
Classifier: Operating System :: MacOS :: MacOS X
Classifier: Operating System :: POSIX :: Linux
Classifier: Topic :: Scientific/Engineering :: Artificial Intelligence
Classifier: Topic :: Scientific/Engineering :: Chemistry
Classifier: Topic :: Scientific/Engineering :: Physics
Classifier: Programming Language :: Python :: 3.10
Classifier: Programming Language :: Python :: 3.11
Classifier: Programming Language :: Python :: 3.12
Requires-Python: >=3.9
License-File: LICENSE
Requires-Dist: dm-haiku>0.0.9
Requires-Dist: h5py
Requires-Dist: hydra-core
Requires-Dist: jax
Requires-Dist: jaxlib
Requires-Dist: jax-dataclasses
Requires-Dist: kfac-jax
Requires-Dist: scipy
Requires-Dist: optax
Requires-Dist: pyscf
Requires-Dist: tensorboardX
Requires-Dist: pyyaml
Requires-Dist: tqdm
Requires-Dist: uncertainties
Requires-Dist: chex<1.0.0
Provides-Extra: dev
Requires-Dist: pytest; extra == "dev"
Requires-Dist: pytest-regressions; extra == "dev"
Requires-Dist: black; extra == "dev"
Requires-Dist: codespell; extra == "dev"
Requires-Dist: flake8; extra == "dev"
Requires-Dist: flake8-bugbear; extra == "dev"
Requires-Dist: flake8-comprehensions; extra == "dev"
Requires-Dist: flake8-quotes; extra == "dev"
Requires-Dist: isort; extra == "dev"
Requires-Dist: mypy; extra == "dev"
Requires-Dist: pep8-naming; extra == "dev"
Requires-Dist: pre-commit; extra == "dev"
Requires-Dist: pydocstyle; extra == "dev"
Requires-Dist: pyright; extra == "dev"
Provides-Extra: doc
Requires-Dist: sphinx; extra == "doc"
Requires-Dist: Jinja2; extra == "doc"
Requires-Dist: sphinxcontrib-katex; extra == "doc"
Requires-Dist: toml; extra == "doc"
Requires-Dist: docutils; extra == "doc"
Requires-Dist: pydata-sphinx-theme; extra == "doc"
